LICENSE
README.md
setup.py
media/The_Pier.png
pebcaw/__init__.py
pebcaw.egg-info/PKG-INFO
pebcaw.egg-info/SOURCES.txt
pebcaw.egg-info/dependency_links.txt
pebcaw.egg-info/entry_points.txt
pebcaw.egg-info/not-zip-safe
pebcaw.egg-info/requires.txt
pebcaw.egg-info/top_level.txt