Metadata-Version: 1.0
Name: pebcaw
Version: 2020.2.18.12
Summary: monitor internet connection security
Home-page: https://github.com/wdbm/pebcaw
Author: Will Breaden Madden
Author-email: wbm@protonmail.ch
License: GPLv3
Platform: UNKNOWN
